MANIFEST.in
README.md
setup.cfg
setup.py
versioneer.py
test/__init__.py
test/test_control_utils.py
ulog_tools/__init__.py
ulog_tools/_control.py
ulog_tools/_lqrofb.py
ulog_tools/_sysid.py
ulog_tools/_ulog.py
ulog_tools/_version.py
ulog_tools/control_opt.py
ulog_tools.egg-info/PKG-INFO
ulog_tools.egg-info/SOURCES.txt
ulog_tools.egg-info/dependency_links.txt
ulog_tools.egg-info/entry_points.txt
ulog_tools.egg-info/requires.txt
ulog_tools.egg-info/top_level.txt