Metadata-Version: 1.2
Name: ulog-tools
Version: 0.0.9
Summary: Ulog process tools
Home-page: https://github.com/dronecrew/ulog_tools
Author: James Goppert
Author-email: james.goppert@gmail.com
Maintainer: James Goppert
Maintainer-email: james.goppert@gmail.com
License: BSD 3-Clause
Download-URL: https://github.com/dronecrew/ulog_tools
Platform: Windows
Platform: Linux
Platform: Solaris
Platform: Mac OS-X
Platform: Unix
Classifier: Development Status :: 1 - Planning
Classifier: Intended Audience :: Science/Research
Classifier: Intended Audience :: Developers
Classifier: License :: OSI Approved :: BSD License
Classifier: Programming Language :: Python
Classifier: Programming Language :: Python :: 3
Classifier: Programming Language :: Other
Classifier: Topic :: Software Development
Classifier: Topic :: Scientific/Engineering :: Artificial Intelligence
Classifier: Topic :: Scientific/Engineering :: Mathematics
Classifier: Topic :: Scientific/Engineering :: Physics
Classifier: Operating System :: Microsoft :: Windows
Classifier: Operating System :: POSIX
Classifier: Operating System :: Unix
Classifier: Operating System :: MacOS
